FabOMatic/__init__.py
FabOMatic/__main__.py
FabOMatic/babel.cfg
FabOMatic/logger.py
FabOMatic/alembic/README
FabOMatic/alembic/env.py
FabOMatic/alembic/script.py.mako
FabOMatic/alembic/versions/123b2cca325f_added_boards_table.py
FabOMatic/alembic/versions/2dc275252e0e_initial_database_creation.py
FabOMatic/alembic/versions/3cb12dfd8d6e_maintenance_added_short_lcd_message.py
FabOMatic/alembic/versions/3f3f601505a6_added_replay_columns_for_use_and_.py
FabOMatic/alembic/versions/88feb1b31a1f_added_grace_period_column_on_machinetype.py
FabOMatic/alembic/versions/aa9ed3e094d5_maintenance_added_url_field_and_removed_.py
FabOMatic/alembic/versions/dfd2b0db0016_machine_types_added_possibility_to_.py
FabOMatic/alembic/versions/e544554c7d29_boards_added_columns_for_serial_number_.py
FabOMatic/conf/FabConfig.py
FabOMatic/conf/__init__.py
FabOMatic/conf/settings.example.toml
FabOMatic/conf/settings.toml
FabOMatic/database/DatabaseBackend.py
FabOMatic/database/__init__.py
FabOMatic/database/constants.py
FabOMatic/database/models.py
FabOMatic/database/repositories.py
FabOMatic/flask_app/static/css/all.css
FabOMatic/flask_app/static/css/all.min.css
FabOMatic/flask_app/static/css/bootstrap-grid.css
FabOMatic/flask_app/static/css/bootstrap-grid.css.map
FabOMatic/flask_app/static/css/bootstrap-grid.min.css
FabOMatic/flask_app/static/css/bootstrap-grid.min.css.map
FabOMatic/flask_app/static/css/bootstrap-grid.rtl.css
FabOMatic/flask_app/static/css/bootstrap-grid.rtl.css.map
FabOMatic/flask_app/static/css/bootstrap-grid.rtl.min.css
FabOMatic/flask_app/static/css/bootstrap-grid.rtl.min.css.map
FabOMatic/flask_app/static/css/bootstrap-reboot.css
FabOMatic/flask_app/static/css/bootstrap-reboot.css.map
FabOMatic/flask_app/static/css/bootstrap-reboot.min.css
FabOMatic/flask_app/static/css/bootstrap-reboot.min.css.map
FabOMatic/flask_app/static/css/bootstrap-reboot.rtl.css
FabOMatic/flask_app/static/css/bootstrap-reboot.rtl.css.map
FabOMatic/flask_app/static/css/bootstrap-reboot.rtl.min.css
fabomatic-0.7.2.dist-info/METADATA
fabomatic-0.7.2.dist-info/WHEEL
fabomatic-0.7.2.dist-info/licenses/LICENSE
fabomatic-0.7.2.dist-info/RECORD
