Metadata-Version: 2.4
Name: FabOMatic
Version: 0.7.2
Summary: Backend for Fab-O-Matic RFID boards
Project-URL: Homepage, https://github.com/fablab-bergamo/fabomatic-backend
Project-URL: Bug Tracker, https://github.com/fablab-bergamo/fabomatic-backend/issues
Author-email: Lorenzo Rossi <mail@lorenzoros.si>, Pascal Brunot <pbr-dev@gmail.com>, Valerio Nappi <valerionappi995@gmail.com>
License-File: LICENSE
Classifier: License :: OSI Approved :: MIT License
Classifier: Operating System :: OS Independent
Classifier: Programming Language :: Python :: 3
Requires-Python: >=3.10
Requires-Dist: alembic
Requires-Dist: colorlog
Requires-Dist: flask-babel
Requires-Dist: flask-excel
Requires-Dist: flask-login
Requires-Dist: flask-mail
Requires-Dist: flask>=3.0.0
Requires-Dist: itsdangerous
Requires-Dist: paho-mqtt==2.1.0
Requires-Dist: psutil
Requires-Dist: pyexcel-xlsx
Requires-Dist: pyopenssl
Requires-Dist: requests
Requires-Dist: sqlalchemy>=2.0.25
Requires-Dist: toml==0.10.2
Provides-Extra: dev
Requires-Dist: pytest; extra == 'dev'
Requires-Dist: pytest-cov; extra == 'dev'
